tap_googleads/__init__.py
tap_googleads/auth.py
tap_googleads/client.py
tap_googleads/schemas/ad_group.json
tap_googleads/schemas/ad_group_performance.json
tap_googleads/schemas/campaign.json
tap_googleads/schemas/campaign_label.json
tap_googleads/schemas/campaign_performance.json
tap_googleads/schemas/campaign_performance_by_age_range_and_device.json
tap_googleads/schemas/campaign_performance_by_gender_and_device.json
tap_googleads/schemas/campaign_performance_by_location.json
tap_googleads/schemas/conversion_by_location.json
tap_googleads/schemas/customer.json
tap_googleads/schemas/customer_hierarchy.json
tap_googleads/schemas/geo_target_constant.json
tap_googleads/streams.py
tap_googleads/tap.py
tap_googleads/tests/__init__.py
tap_googleads/tests/test_core.py
tap_googleads/tests/test_customer_not_found.py
tap_googleads/tests/test_utils.py
tap_googleads/utils.py
tap_googleads-0.1.7.dist-info/METADATA
tap_googleads-0.1.7.dist-info/WHEEL
tap_googleads-0.1.7.dist-info/entry_points.txt
tap_googleads-0.1.7.dist-info/RECORD
