Metadata-Version: 2.1
Name: tap-googleads
Version: 0.1.7
Summary: `tap-googleads` is a Singer tap for GoogleAds, built with the Meltano SDK for Singer Taps.
License: Apache 2.0
Keywords: ELT,GoogleAds
Author: AutoIDM
Requires-Python: >=3.8,<3.11
Classifier: License :: Other/Proprietary License
Classifier: Programming Language :: Python :: 3
Classifier: Programming Language :: Python :: 3.8
Classifier: Programming Language :: Python :: 3.9
Classifier: Programming Language :: Python :: 3.10
Requires-Dist: requests (>=2.25.1,<3.0.0)
Requires-Dist: singer-sdk (==0.29.0)
